websocietysimulator/__init__.py
websocietysimulator/agent/__init__.py
websocietysimulator/agent/agent.py
websocietysimulator/agent/modules/__init__.py
websocietysimulator/agent/modules/memory_modules.py
websocietysimulator/agent/modules/planning_modules.py
websocietysimulator/agent/modules/reasoning_modules.py
websocietysimulator/agent/modules/tooluse_modules.py
websocietysimulator/agent/modules/tooluse_pool.py
websocietysimulator/agent/recommendation_agent.py
websocietysimulator/agent/simulation_agent.py
websocietysimulator/llm/__init__.py
websocietysimulator/llm/infinigence_embeddings.py
websocietysimulator/llm/llm.py
websocietysimulator/simulator.py
websocietysimulator/tasks/__init__.py
websocietysimulator/tasks/recommendation_task.py
websocietysimulator/tasks/simulation_task.py
websocietysimulator/tools/__init__.py
websocietysimulator/tools/cache_interaction_tool.py
websocietysimulator/tools/evaluation_tool.py
websocietysimulator/tools/interaction_tool.py
websocietysimulator-1.0.0a25.dist-info/LICENSE
websocietysimulator-1.0.0a25.dist-info/METADATA
websocietysimulator-1.0.0a25.dist-info/WHEEL
websocietysimulator-1.0.0a25.dist-info/RECORD
