Metadata-Version: 2.3
Name: websocietysimulator
Version: 1.0.0a25
Summary: Web Social Simulator for WWW'25 AgentSociety Challenge
License: MIT
Author: Yuwei Yan
Author-email: yyan791@connect.hkust-gz.edu.cn
Requires-Python: >=3.10,<4.0
Classifier: License :: OSI Approved :: MIT License
Classifier: Programming Language :: Python :: 3
Classifier: Programming Language :: Python :: 3.10
Classifier: Programming Language :: Python :: 3.11
Classifier: Programming Language :: Python :: 3.12
Classifier: Programming Language :: Python :: 3.13
Requires-Dist: langchain (>=0.3.13,<0.4.0)
Requires-Dist: langchain-chroma (>=0.1.4,<0.2.0)
Requires-Dist: langchain-openai (>=0.2.14,<0.3.0)
Requires-Dist: lmdb (>=1.6.2,<2.0.0)
Requires-Dist: nltk (>=3.9.1,<4.0.0)
Requires-Dist: openai (>=1.58.1,<2.0.0)
Requires-Dist: pandas (>=2.2.3,<3.0.0)
Requires-Dist: seaborn (>=0.13.2,<0.14.0)
Requires-Dist: sentence-transformers (>=3.3.1,<4.0.0)
Requires-Dist: torch (>=2.5.1,<3.0.0)
Requires-Dist: tqdm (>=4.67.1,<5.0.0)
Requires-Dist: transformers (>=4.47.0,<5.0.0)
